generic_helpers/__init__.py
generic_helpers/checks.py
generic_helpers/decorators.py
generic_helpers/fields.py
generic_helpers/managers.py
generic_helpers/models.py
generic_helpers/settings.py
generic_helpers/utils.py
django_generic_helpers-1.2.0.dist-info/WHEEL
django_generic_helpers-1.2.0.dist-info/METADATA
django_generic_helpers-1.2.0.dist-info/RECORD
