Metadata-Version: 2.1
Name: django-generic-helpers
Version: 1.2.0
Summary: A small toolset that helps you to work with Django's generic relations
Home-page: https://github.com/marazmiki/django-generic-helpers
License: MIT
Keywords: django,framework,relations,generic,generic relations
Author: Mikhail Porokhovnichenko
Author-email: marazmiki@gmail.com
Requires-Python: >=3.6,<4.0
Classifier: Development Status :: 5 - Production/Stable
Classifier: Environment :: Web Environment
Classifier: Framework :: Django
Classifier: Framework :: Django :: 2.2
Classifier: Framework :: Django :: 3.1
Classifier: Framework :: Django :: 3.2
Classifier: Framework :: Django :: 4.0
Classifier: Intended Audience :: Developers
Classifier: License :: OSI Approved :: MIT License
Classifier: Operating System :: OS Independent
Classifier: Programming Language :: Python
Classifier: Programming Language :: Python :: 3
Classifier: Programming Language :: Python :: 3.10
Classifier: Programming Language :: Python :: 3.6
Classifier: Programming Language :: Python :: 3.7
Classifier: Programming Language :: Python :: 3.8
Classifier: Programming Language :: Python :: 3.9
Project-URL: Repository, https://github.com/marazmiki/django-generic-helpers
